odoo/addons/stock_product_qty_by_packaging/README.rst
odoo/addons/stock_product_qty_by_packaging/__init__.py
odoo/addons/stock_product_qty_by_packaging/__manifest__.py
odoo/addons/stock_product_qty_by_packaging/i18n/fr.po
odoo/addons/stock_product_qty_by_packaging/i18n/it.po
odoo/addons/stock_product_qty_by_packaging/i18n/stock_product_qty_by_packaging.pot
odoo/addons/stock_product_qty_by_packaging/models/__init__.py
odoo/addons/stock_product_qty_by_packaging/models/stock_move.py
odoo/addons/stock_product_qty_by_packaging/models/stock_move_line.py
odoo/addons/stock_product_qty_by_packaging/models/stock_quant.py
odoo/addons/stock_product_qty_by_packaging/readme/CONTRIBUTORS.md
odoo/addons/stock_product_qty_by_packaging/readme/CREDITS.md
odoo/addons/stock_product_qty_by_packaging/readme/DESCRIPTION.md
odoo/addons/stock_product_qty_by_packaging/static/description/icon.png
odoo/addons/stock_product_qty_by_packaging/static/description/index.html
odoo/addons/stock_product_qty_by_packaging/tests/__init__.py
odoo/addons/stock_product_qty_by_packaging/tests/test_stock.py
odoo/addons/stock_product_qty_by_packaging/views/stock_picking.xml
odoo_addon_stock_product_qty_by_packaging-18.0.1.0.1.dist-info/METADATA
odoo_addon_stock_product_qty_by_packaging-18.0.1.0.1.dist-info/WHEEL
odoo_addon_stock_product_qty_by_packaging-18.0.1.0.1.dist-info/top_level.txt
odoo_addon_stock_product_qty_by_packaging-18.0.1.0.1.dist-info/RECORD
